cyged-0.2.3.dist-info/RECORD
cyged-0.2.3.dist-info/top_level.txt
cyged-0.2.3.dist-info/WHEEL
cyged-0.2.3.dist-info/METADATA
cyged-0.2.3.dist-info/LICENSE
cyged/__init__.py
cyged/graph_pkg_core/__init__.py
cyged/graph_pkg_core/utils/reset_compilation.py
cyged/graph_pkg_core/utils/__init__.py
cyged/graph_pkg_core/graph/node.pxd
cyged/graph_pkg_core/graph/node.cpython-39-x86_64-linux-gnu.so
cyged/graph_pkg_core/graph/graph.pxd
cyged/graph_pkg_core/graph/graph.cpython-39-x86_64-linux-gnu.so
cyged/graph_pkg_core/graph/edge.pxd
cyged/graph_pkg_core/graph/edge.cpython-39-x86_64-linux-gnu.so
cyged/graph_pkg_core/graph/__init__.py
cyged/graph_pkg_core/graph/label/label_node_vector.cpython-39-x86_64-linux-gnu.so
cyged/graph_pkg_core/graph/label/label_edge.pxd
cyged/graph_pkg_core/graph/label/label_edge.cpython-39-x86_64-linux-gnu.so
cyged/graph_pkg_core/graph/label/label_base.pxd
cyged/graph_pkg_core/graph/label/label_base.cpython-39-x86_64-linux-gnu.so
cyged/graph_pkg_core/graph/label/__init__.py
cyged/graph_pkg_core/edit_cost/metrics.pxd
cyged/graph_pkg_core/edit_cost/metrics.cpython-39-x86_64-linux-gnu.so
cyged/graph_pkg_core/edit_cost/edit_cost_vector.pxd
cyged/graph_pkg_core/edit_cost/edit_cost_vector.cpython-39-x86_64-linux-gnu.so
cyged/graph_pkg_core/edit_cost/edit_cost.pxd
cyged/graph_pkg_core/edit_cost/edit_cost.cpython-39-x86_64-linux-gnu.so
cyged/graph_pkg_core/edit_cost/__init__.py
cyged/graph_pkg_core/coordinator/graph_loader.cpython-39-x86_64-linux-gnu.so
cyged/graph_pkg_core/coordinator/coordinator.cpython-39-x86_64-linux-gnu.so
cyged/graph_pkg_core/coordinator/__init__.py
cyged/graph_pkg_core/algorithm/matrix_distances.pxd
cyged/graph_pkg_core/algorithm/matrix_distances.cpython-39-x86_64-linux-gnu.so
cyged/graph_pkg_core/algorithm/graph_edit_distance.pxd
cyged/graph_pkg_core/algorithm/graph_edit_distance.cpython-39-x86_64-linux-gnu.so
cyged/graph_pkg_core/algorithm/__init__.py
