Metadata-Version: 2.1
Name: cyged
Version: 0.2.3
Summary: A python module to compute GED using cython
Author: Anthony Gillioz
Author-email: Anthony Gillioz <anthony.gillioz@outlook.com>
Project-URL: Homepage, https://github.com/CheshireCat12/graph-matching-core
Project-URL: Bug Tracker, https://github.com/CheshireCat12/graph-matching-core/issues
Classifier: Programming Language :: Python :: 3
Classifier: License :: OSI Approved :: MIT License
Classifier: Operating System :: OS Independent
Requires-Python: <=3.10
License-File: LICENSE
Requires-Dist: bunch
Requires-Dist: easydict
Requires-Dist: gitpython
Requires-Dist: networkx
Requires-Dist: pandas
Requires-Dist: powerline-status
Requires-Dist: progress
Requires-Dist: psutil
Requires-Dist: pytest
Requires-Dist: pyyaml
Requires-Dist: scipy
Requires-Dist: tqdm
Requires-Dist: xmltodict
Requires-Dist: wheel
